nyzostrings/__init__.py
nyzostrings/nyzostring.py
nyzostrings/nyzostringencoder.py
nyzostrings/nyzostringmicropay.py
nyzostrings/nyzostringprefilleddata.py
nyzostrings/nyzostringprivateseed.py
nyzostrings/nyzostringpublicidentifier.py
nyzostrings/nyzostringsignature.py
nyzostrings/nyzostringtransaction.py
Nyzostrings-0.0.7.dist-info/AUTHORS.rst
Nyzostrings-0.0.7.dist-info/LICENSE
Nyzostrings-0.0.7.dist-info/METADATA
Nyzostrings-0.0.7.dist-info/WHEEL
Nyzostrings-0.0.7.dist-info/top_level.txt
Nyzostrings-0.0.7.dist-info/RECORD
