Metadata-Version: 2.1
Name: Nyzostrings
Version: 0.0.7
Summary: nyzostrings PIP module for Nyzo cryptocurrency. Handles Conversion to and from nyzostrings.
Home-page: https://github.com/angainordev/nyzostrings
Author: EggdraSyl from Bismuth Foundation
Author-email: dev@eggpool.net
License: MIT license
Keywords: nyzostrings
Platform: UNKNOWN
Classifier: Development Status :: 5 - Production/Stable
Classifier: Intended Audience :: Developers
Classifier: License :: OSI Approved :: MIT License
Classifier: Natural Language :: English
Classifier: Programming Language :: Python :: 3.6
Classifier: Programming Language :: Python :: 3.7
